ctcloudsdkcore/__init__.py
ctcloudsdkcore/client.py
ctcloudsdkcore/sdk_request.py
ctcloudsdkcore/sdk_response.py
ctcloudsdkcore/sdk_stream_request.py
ctcloudsdkcore/sdk_stream_response.py
ctcloudsdkcore/auth/__init__.py
ctcloudsdkcore/auth/cache.py
ctcloudsdkcore/auth/credentials.py
ctcloudsdkcore/auth/internal.py
ctcloudsdkcore/auth/provider.py
ctcloudsdkcore/exceptions/__init__.py
ctcloudsdkcore/exceptions/exception_handler.py
ctcloudsdkcore/exceptions/exceptions.py
ctcloudsdkcore/http/__init__.py
ctcloudsdkcore/http/formdata.py
ctcloudsdkcore/http/future_session.py
ctcloudsdkcore/http/http_client.py
ctcloudsdkcore/http/http_config.py
ctcloudsdkcore/http/http_handler.py
ctcloudsdkcore/http/primitive_types.py
ctcloudsdkcore/http/progress.py
ctcloudsdkcore/invoker/__init__.py
ctcloudsdkcore/invoker/invoker.py
ctcloudsdkcore/region/__init__.py
ctcloudsdkcore/region/cache.py
ctcloudsdkcore/region/provider.py
ctcloudsdkcore/region/region.py
ctcloudsdkcore/signer/__init__.py
ctcloudsdkcore/signer/algorithm.py
ctcloudsdkcore/signer/gm.py
ctcloudsdkcore/signer/hkdf.py
ctcloudsdkcore/signer/signer.py
ctcloudsdkcore/utils/__init__.py
ctcloudsdkcore/utils/core_utils.py
ctcloudsdkcore/utils/filepath_utils.py
ctcloudsdkcore/utils/http_utils.py
ctcloudsdkcore/utils/six_utils.py
ctcloudsdkcore/utils/string_utils.py
ctcloudsdkcore/utils/time_utils.py
ctcloudsdkcore/utils/xml_utils.py
ctcloudsdkcore-0.0.1b0.dist-info/LICENSE
ctcloudsdkcore-0.0.1b0.dist-info/METADATA
ctcloudsdkcore-0.0.1b0.dist-info/WHEEL
ctcloudsdkcore-0.0.1b0.dist-info/top_level.txt
ctcloudsdkcore-0.0.1b0.dist-info/RECORD
