Metadata-Version: 2.1
Name: ctcloudsdkcore
Version: 0.0.1b0
Summary: CtCloud SDK Python Core
Home-page: https://github.com/ctcloud-sdk/ctcloud-sdk-python
Author: CtCloud SDK
Author-email: unionsdk@outlook.com
License: Apache LICENSE 2.0
Keywords: ctcloud,sdk,core
Platform: any
Classifier: Development Status :: 5 - Production/Stable
Classifier: Intended Audience :: Developers
Classifier: License :: OSI Approved :: Apache Software License
Classifier: Programming Language :: Python :: 2.7
Classifier: Programming Language :: Python :: 3.3
Classifier: Programming Language :: Python :: 3.4
Classifier: Programming Language :: Python :: 3.5
Classifier: Programming Language :: Python :: 3.6
Classifier: Programming Language :: Python :: 3.7
Classifier: Programming Language :: Python :: 3.8
Classifier: Programming Language :: Python :: 3.9
Classifier: Topic :: Software Development
Requires-Python: >=2.7,!=3.0.*,!=3.1.*,!=3.2.*
License-File: LICENSE
Requires-Dist: requests
Requires-Dist: requests-toolbelt >=0.10.1
Requires-Dist: six >=1.16.0
Requires-Dist: simplejson >=3.18.0
Requires-Dist: PyYAML >=5.4.1
Requires-Dist: ecdsa >=0.18.0
Requires-Dist: typing-extensions
Provides-Extra: python_version_2.7_
Requires-Dist: futures >=3.3.0 ; extra == 'python_version_2.7_'
Requires-Dist: configparser >=4.0.2 ; extra == 'python_version_2.7_'
Requires-Dist: certifi >=2022.12.7 ; extra == 'python_version_2.7_'
